Hoi4Converter/__init__.py
Hoi4Converter/converter.py
Hoi4Converter/mappings.py
Hoi4Converter/parser.py
hoi4_converter-1.1.dist-info/LICENSE
hoi4_converter-1.1.dist-info/METADATA
hoi4_converter-1.1.dist-info/WHEEL
hoi4_converter-1.1.dist-info/top_level.txt
hoi4_converter-1.1.dist-info/RECORD
